bitrix24/__init__.py
bitrix24/bitrix24.py
bitrix24/exceptions.py
bitrix24/utils.py
tests/__init__.py
tests/test_calls.py
tests/test_headless.py
tests/test_tokens.py
bitrix24_python3_client-0.4.0.dist-info/LICENSE.txt
bitrix24_python3_client-0.4.0.dist-info/METADATA
bitrix24_python3_client-0.4.0.dist-info/WHEEL
bitrix24_python3_client-0.4.0.dist-info/top_level.txt
bitrix24_python3_client-0.4.0.dist-info/RECORD
