Metadata-Version: 2.1
Name: bitrix24-python3-client
Version: 0.4.0
Summary: A tiny Python3 client to make requests of Bitrix24 API.
Home-page: https://github.com/yarbshk/bitrix24-python3-client
Author: Yuriy Rabeshko
Author-email: george.rabeshko@gmail.com
License: MIT
Keywords: bitrix24 api rest python3 client
Platform: any
Classifier: Development Status :: 4 - Beta
Classifier: Intended Audience :: Developers
Classifier: License :: OSI Approved :: MIT License
Classifier: Natural Language :: English
Classifier: Programming Language :: Python :: 3
Classifier: Topic :: Software Development :: Libraries :: Python Modules
Requires-Python: >=3
Requires-Dist: requests (>=2.18.0)
